topsis/__init__.py
topsis/topsis.py
topsis_rajgupta_102303324-1.0.3.dist-info/METADATA
topsis_rajgupta_102303324-1.0.3.dist-info/WHEEL
topsis_rajgupta_102303324-1.0.3.dist-info/entry_points.txt
topsis_rajgupta_102303324-1.0.3.dist-info/top_level.txt
topsis_rajgupta_102303324-1.0.3.dist-info/RECORD
