Metadata-Version: 2.4
Name: topsis-rajgupta-102303324
Version: 1.0.3
Summary: TOPSIS implementation using Python
Author: Raj Gupta
Requires-Python: >=3.7
Requires-Dist: pandas
Requires-Dist: numpy
Dynamic: author
Dynamic: description
Dynamic: description-content-type
Dynamic: requires-dist
Dynamic: requires-python
Dynamic: summary
